[{"al": "demo", "name": "Demo (1).jpg", "h": 1080, "w": 1329, "ct": 1715434567.494127, "faces": [[458, 311, 71, 71]]}, {"al": "demo", "name": "Demo (1).png", "h": 720, "w": 720, "ct": 1715434567.495556, "faces": [[244, 98, 310, 310]]}, {"al": "demo", "name": "Demo (5).gif", "h": 480, "w": 480, "ct": 1715434567.4966142, "faces": []}, {"al": "demo", "name": "Demo (5).jpeg", "h": 2402, "w": 1600, "ct": 1715434567.4972515, "faces": [[554, 442, 383, 383], [562, 1536, 32, 32]]}, {"al": "demo", "name": "Demo (1).jpeg", "h": 1080, "w": 1080, "ct": 1715434567.4977124, "faces": [[315, 267, 309, 309]]}, {"al": "demo", "name": "Demo (4).gif", "h": 374, "w": 640, "ct": 1715434567.4987292, "faces": []}, {"al": "demo", "name": "Demo (3).jpeg", "h": 1611, "w": 1600, "ct": 1715434567.499856, "faces": [[128, 987, 74, 74]]}, {"al": "demo", "name": "Demo (3).gif", "h": 720, "w": 720, "ct": 1715434567.5020251, "faces": []}, {"al": "demo", "name": "Demo (4).jpeg", "h": 2401, "w": 1600, "ct": 1715434567.506754, "faces": [[1304, 309, 163, 163], [602, 354, 558, 558]]}, {"al": "demo", "name": "Demo (2).jpeg", "h": 600, "w": 600, "ct": 1715434567.509308, "faces": [[226, 83, 242, 242]]}, {"al": "demo", "name": "Demo (2).gif", "h": 778, "w": 567, "ct": 1715434567.511594, "faces": []}, {"al": "demo", "name": "Demo (1).gif", "h": 850, "w": 850, "ct": 1715434567.515325, "faces": []}, {"al": "demo", "name": "Demo (5).png", "h": 720, "w": 720, "ct": 1715434567.5161123, "faces": [[196, 174, 150, 150]]}, {"al": "demo", "name": "Demo (5).jpg", "h": 1080, "w": 1080, "ct": 1715434567.524715, "faces": [[330, 177, 400, 400]]}, {"al": "demo", "name": "Demo (4).jpg", "h": 1922, "w": 1080, "ct": 1715434567.5253816, "faces": [[533, 158, 316, 316], [582, 1298, 67, 67]]}, {"al": "demo", "name": "Demo (4).png", "h": 720, "w": 720, "ct": 1715434567.526162, "faces": [[191, 202, 143, 143]]}, {"al": "demo", "name": "Demo (3).png", "h": 720, "w": 720, "ct": 1715434567.5272925, "faces": [[192, 116, 222, 222]]}, {"al": "demo", "name": "Demo (3).jpg", "h": 1440, "w": 1440, "ct": 1715434567.52839, "faces": [[728, 6, 85, 85], [872, 26, 88, 88], [296, 129, 143, 143], [454, 323, 431, 431], [107, 340, 105, 105], [874, 1026, 59, 59]]}, {"al": "demo", "name": "Demo (2).jpg", "h": 800, "w": 800, "ct": 1715434567.5289128, "faces": [[294, 166, 260, 260]]}, {"al": "demo", "name": "Demo (2).png", "h": 720, "w": 720, "ct": 1715434567.5301466, "faces": [[331, 171, 336, 336]]}, {"al": "aaaaa", "name": "cy (41).jpg", "h": 1620, "w": 1080, "ct": 1715434567.5330179, "faces": [[400, 266, 256, 256]]}, {"al": "aaaaa", "name": "cy (16).jpg", "h": 1440, "w": 1080, "ct": 1715434567.5351472, "faces": [[417, 445, 351, 351]]}, {"al": "aaaaa", "name": "cy (5).jpg", "h": 1800, "w": 1080, "ct": 1715434567.5356236, "faces": [[29, 162, 262, 262], [454, 534, 86, 86], [460, 1028, 130, 130]]}, {"al": "aaaaa", "name": "cy (57).jpg", "h": 1598, "w": 1080, "ct": 1715434567.5360246, "faces": [[558, 263, 134, 134], [491, 269, 467, 467]]}, {"al": "aaaaa", "name": "cy (94).jpg", "h": 1801, "w": 1080, "ct": 1715434567.5368335, "faces": [[542, 238, 250, 250], [64, 768, 156, 156], [15, 508, 203, 203], [137, 1378, 53, 53], [140, 1395, 59, 59]]}, {"al": "aaaaa", "name": "cy (82).jpg", "h": 1800, "w": 1080, "ct": 1715434567.5372036, "faces": [[485, 227, 177, 177]]}, {"al": "aaaaa", "name": "cy (107).jpg", "h": 1620, "w": 1080, "ct": 1715434567.5377138, "faces": [[548, 178, 134, 134], [449, 547, 94, 94], [618, 1060, 47, 47]]}, {"al": "aaaaa", "name": "cy (9).jpg", "h": 1592, "w": 895, "ct": 1715434567.5380993, "faces": [[321, 145, 240, 240]]}, {"al": "aaaaa", "name": "cy (1).gif", "h": 1080, "w": 1080, "ct": 1715434567.5408459, "faces": []}, {"al": "aaaaa", "name": "cy (20).jpg", "h": 1620, "w": 1080, "ct": 1715434567.5415108, "faces": [[426, 179, 229, 229]]}, {"al": "aaaaa", "name": "cy (98).jpg", "h": 1619, "w": 1080, "ct": 1715434567.5479288, "faces": [[127, 319, 93, 93], [471, 217, 186, 186]]}, {"al": "aaaaa", "name": "cy (77).jpg", "h": 1620, "w": 1080, "ct": 1715434567.548366, "faces": [[389, 291, 396, 396]]}, {"al": "aaaaa", "name": "cy (61).jpg", "h": 1620, "w": 1080, "ct": 1715434567.548871, "faces": [[422, 179, 263, 263], [221, 535, 127, 127]]}, {"al": "aaaaa", "name": "cy (36).jpg", "h": 1801, "w": 1080, "ct": 1715434567.5494514, "faces": [[801, 914, 93, 93]]}, {"al": "aaaaa", "name": "cy (37).jpg", "h": 1620, "w": 1080, "ct": 1715434567.549874, "faces": [[485, 224, 169, 169], [337, 834, 107, 107]]}, {"al": "aaaaa", "name": "cy (60).jpg", "h": 1620, "w": 1080, "ct": 1715434567.550291, "faces": [[435, 143, 196, 196]]}, {"al": "aaaaa", "name": "cy (99).jpg", "h": 1620, "w": 1080, "ct": 1715434567.5507886, "faces": [[740, 629, 124, 124], [168, 671, 265, 265]]}, {"al": "aaaaa", "name": "cy (76).jpg", "h": 540, "w": 810, "ct": 1715434567.5510857, "faces": []}, {"al": "aaaaa", "name": "cy (21).jpg", "h": 1077, "w": 1077, "ct": 1715434567.551692, "faces": [[242, 181, 486, 486], [424, 819, 196, 196], [87, 873, 80, 80]]}, {"al": "aaaaa", "name": "cy (8).jpg", "h": 1801, "w": 1080, "ct": 1715434567.552081, "faces": [[565, 813, 101, 101]]}, {"al": "aaaaa", "name": "cy (106).jpg", "h": 1620, "w": 1080, "ct": 1715434567.5524979, "faces": [[713, 214, 62, 62], [552, 119, 147, 147], [720, 196, 98, 98]]}, {"al": "aaaaa", "name": "cy (83).jpg", "h": 1440, "w": 1080, "ct": 1715434567.5529313, "faces": [[680, 369, 103, 103], [212, 387, 124, 124], [545, 481, 131, 131], [910, 799, 103, 103]]}, {"al": "aaaaa", "name": "cy (95).jpg", "h": 1801, "w": 1080, "ct": 1715434567.5574272, "faces": [[423, 862, 215, 215]]}, {"al": "aaaaa", "name": "cy (56).jpg", "h": 1642, "w": 1080, "ct": 1715434567.5578117, "faces": []}, {"al": "aaaaa", "name": "cy (4).jpg", "h": 1801, "w": 1080, "ct": 1715434567.5582225, "faces": [[379, 196, 398, 398], [50, 145, 440, 440]]}, {"al": "aaaaa", "name": "cy (17).jpg", "h": 1620, "w": 1080, "ct": 1715434567.5586002, "faces": [[357, 302, 467, 467]]}, {"al": "aaaaa", "name": "cy (40).jpg", "h": 1620, "w": 1080, "ct": 1715434567.558978, "faces": [[613, 366, 206, 206], [370, 511, 57, 57]]}, {"al": "aaaaa", "name": "cy (101).jpg", "h": 1620, "w": 1080, "ct": 1715434567.55934, "faces": [[446, 322, 162, 162], [787, 321, 163, 163], [146, 1007, 31, 31], [354, 1407, 134, 134]]}, {"al": "aaaaa", "name": "cy (26).jpg", "h": 1620, "w": 1080, "ct": 1715434567.5598238, "faces": [[453, 340, 80, 80], [530, 361, 168, 168], [464, 402, 80, 80], [475, 1174, 93, 93]]}, {"al": "aaaaa", "name": "cy (71).jpg", "h": 1620, "w": 1080, "ct": 1715434567.5602124, "faces": [[35, 87, 75, 75], [468, 549, 216, 216], [256, 1362, 147, 147]]}]